{
  "meta": {
    "build": {
      "build-date": "2026-07-14",
      "codified-date": "2026-05-15",
      "platform": {
        "reproducible": "false",
        "version": "2.19.5.dev402"
      },
      "repositories": [
        {
          "commit": "a7812a2fb9c417af800b489f973b261dc89c453e",
          "name": "chickasawnation/law-xml"
        },
        {
          "commit": "aa5d34ef993e4933750dbc8c0d027c59c1ceed3b",
          "name": "chickasawnation/law-xml-codified-preview"
        }
      ],
      "search": {
        "version": "v2"
      }
    },
    "canonical-urls": {
      "html": "",
      "html-bulk": "https://github.com/chickasawnation/law-html",
      "static-assets": "https://github.com/chickasawnation/law-static-assets",
      "xml-bulk": "https://github.com/chickasawnation/law-xml"
    },
    "contact": {
      "email": "help@openlawlib.org"
    },
    "description": ""
  }
}