{
  "meta": {
    "build": {
      "build-date": "2026-05-08",
      "codified-date": "2026-02-20",
      "platform": {
        "reproducible": "false",
        "version": "2.19.5.dev402"
      },
      "repositories": [
        {
          "commit": "1cd7efe569cf3954f638f19cc64e05cea23b8b0b",
          "name": "chickasawnation/law-xml"
        },
        {
          "commit": "db6b7e7069dc3bf515ead8e21d87ea67f1b40cf0",
          "name": "chickasawnation/law-xml-codified-preview"
        }
      ],
      "search": {
        "version": "v2"
      }
    },
    "canonical-urls": {
      "html": "",
      "html-bulk": "https://github.com/chickasawnation/law-html",
      "static-assets": "https://github.com/chickasawnation/law-static-assets",
      "xml-bulk": "https://github.com/chickasawnation/law-xml"
    },
    "contact": {
      "email": "help@openlawlib.org"
    },
    "description": ""
  }
}